Binary_free_running_counter/b_counter.v
module b_counter
#(parameter N = 4) 
(
input wire clk,reset,cnt_start,
input wire[N-1:0]start,
output reg[N-1:0] q

);
reg[N-1:0] r_next,r_reg;
always @(posedge clk,posedge reset)//memory
begin
    if(reset==1'b0)
    r_reg<=r_next;
    else
    r_reg<=0;
end
always@*//next state logic
begin
    if(cnt_start==1'b0)
    r_next=r_reg+1;
    else
    r_next=start;
end
always@*
begin//out logic
    q<=r_reg;
end
endmodule

Binary_free_running_counter/b_counter_tb.v
`timescale 1ns/1ps
module b_counter_tb();

localparam N = 8;
reg clk,reset,cnt_start;
reg[N-1:0]start;
wire[N-1:0]q;

b_counter #(.N(N))count
(
.clk(clk),
.reset(reset),
.start(start),
.q(q),
.cnt_start(cnt_start)
);
always
begin
    clk=1'b0;
    #20;
    clk=1'b1;
    #20;
end
initial begin
    $dumpfile("count_wave.vcd");
    $dumpvars(0,b_counter_tb);
    cnt_start=1'b1;
    reset=1'b0;
    start=0;
    #20
    cnt_start=1'b0;
    #400000;
    $finish;
end
initial begin
    $monitor(" clk=%b || Q= %b",clk,q);
end
endmodule

Binary_free_running_counter/count_wave.vcd
$date
	Thu Oct 27 00:09:29 2022
$end
$version
	Icarus Verilog
$end
$timescale
	1ps
$end
$scope module b_counter_tb $end
$var wire 8 ! q [7:0] $end
$var parameter 32 " N $end
$var reg 1 # clk $end
$var reg 1 $ cnt_start $end
$var reg 1 % reset $end
$var reg 8 & start [7:0] $end
$scope module count $end
$var wire 1 # clk $end
$var wire 1 $ cnt_start $end
$var wire 1 % reset $end
$var wire 8 ' start [7:0] $end
$var parameter 32 ( N $end
$var reg 8 ) q [7:0] $end
$var reg 8 * r_next [7:0] $end
$var reg 8 + r_reg [7:0] $end
$upscope $end
$upscope $end
$enddefinitions $end
$comment Show the parameter values. $end
$dumpall
b1000 (
b1000 "
$end
#0
$dumpvars
bx +
b0 *
bx )
b0 '
b0 &
0%
1$
0#
bx !
$end
#20000
b0 !
b0 )
b0 +
b1 *
0$
1#
#40000
0#
#60000
b1 !
b1 )
b10 *
b1 +
1#
#80000
0#
#100000
b10 !
b10 )
b11 *
b10 +
1#
#120000
0#
#140000
b11 !
b11 )
b100 *
b11 +
1#
#160000
0#
#180000
b100 !
b100 )
b101 *
b100 +
1#
#200000
0#
#220000
b101 !
b101 )
b110 *
b101 +
1#
#240000
0#
#260000
b110 !
b110 )
b111 *
b110 +
1#
#280000
0#
#300000
b111 !
b111 )
b1000 *
b111 +
1#
#320000
0#
#340000
b1000 !
b1000 )
b1001 *
b1000 +
1#
#360000
0#
#380000
b1001 !
b1001 )
b1010 *
b1001 +
1#
#400000
0#
#420000
b1010 !
b1010 )
b1011 *
b1010 +
1#
#440000
0#
#460000
b1011 !
b1011 )
b1100 *
b1011 +
1#
#480000
0#
#500000
b1100 !
b1100 )
b1101 *
b1100 +
1#
#520000
0#
#540000
b1101 !
b1101 )
b1110 *
b1101 +
1#
#560000
0#
#580000
b1110 !
b1110 )
b1111 *
b1110 +
1#
#600000
0#
#620000
b1111 !
b1111 )
b10000 *
b1111 +
1#
#640000
0#
#660000
b10000 !
b10000 )
b10001 *
b10000 +
1#
#680000
0#
#700000
b10001 !
b10001 )
b10010 *
b10001 +
1#
#720000
0#
#740000
b10010 !
b10010 )
b10011 *
b10010 +
1#
#760000
0#
#780000
b10011 !
b10011 )
b10100 *
b10011 +
1#
#800000
0#
#820000
b10100 !
b10100 )
b10101 *
b10100 +
1#
#840000
0#
#860000
b10101 !
b10101 )
b10110 *
b10101 +
1#
#880000
0#
#900000
b10110 !
b10110 )
b10111 *
b10110 +
1#
#920000
0#
#940000
b10111 !
b10111 )
b11000 *
b10111 +
1#
#960000
0#
#980000
b11000 !
b11000 )
b11001 *
b11000 +
1#
#1000000
0#
#1020000
b11001 !
b11001 )
b11010 *
b11001 +
1#
#1040000
0#
#1060000
b11010 !
b11010 )
b11011 *
b11010 +
1#
#1080000
0#
#1100000
b11011 !
b11011 )
b11100 *
b11011 +
1#
#1120000
0#
#1140000
b11100 !
b11100 )
b11101 *
b11100 +
1#
#1160000
0#
#1180000
b11101 !
b11101 )
b11110 *
b11101 +
1#
#1200000
0#
#1220000
b11110 !
b11110 )
b11111 *
b11110 +
1#
#1240000
0#
#1260000
b11111 !
b11111 )
b100000 *
b11111 +
1#
#1280000
0#
#1300000
b100000 !
b100000 )
b100001 *
b100000 +
1#
#1320000
0#
#1340000
b100001 !
b100001 )
b100010 *
b100001 +
1#
#1360000
0#
#1380000
b100010 !
b100010 )
b100011 *
b100010 +
1#
#1400000
0#
#1420000
b100011 !
b100011 )
b100100 *
b100011 +
1#
#1440000
0#
#1460000
b100100 !
b100100 )
b100101 *
b100100 +
1#
#1480000
0#
#1500000
b100101 !
b100101 )
b100110 *
b100101 +
1#
#1520000
0#
#1540000
b100110 !
b100110 )
b100111 *
b100110 +
1#
#1560000
0#
#1580000
b100111 !
b100111 )
b101000 *
b100111 +
1#
#1600000
0#
#1620000
b101000 !
b101000 )
b101001 *
b101000 +
1#
#1640000
0#
#1660000
b101001 !
b101001 )
b101010 *
b101001 +
1#
#1680000
0#
#1700000
b101010 !
b101010 )
b101011 *
b101010 +
1#
#1720000
0#
#1740000
b101011 !
b101011 )
b101100 *
b101011 +
1#
#1760000
0#
#1780000
b101100 !
b101100 )
b101101 *
b101100 +
1#
#1800000
0#
#1820000
b101101 !
b101101 )
b101110 *
b101101 +
1#
#1840000
0#
#1860000
b101110 !
b101110 )
b101111 *
b101110 +
1#
#1880000
0#
#1900000
b101111 !
b101111 )
b110000 *
b101111 +
1#
#1920000
0#
#1940000
b110000 !
b110000 )
b110001 *
b110000 +
1#
#1960000
0#
#1980000
b110001 !
b110001 )
b110010 *
b110001 +
1#
#2000000
0#
#2020000
b110010 !
b110010 )
b110011 *
b110010 +
1#
#2040000
0#
#2060000
b110011 !
b110011 )
b110100 *
b110011 +
1#
#2080000
0#
#2100000
b110100 !
b110100 )
b110101 *
b110100 +
1#
#2120000
0#
#2140000
b110101 !
b110101 )
b110110 *
b110101 +
1#
#2160000
0#
#2180000
b110110 !
b110110 )
b110111 *
b110110 +
1#
#2200000
0#
#2220000
b110111 !
b110111 )
b111000 *
b110111 +
1#
#2240000
0#
#2260000
b111000 !
b111000 )
b111001 *
b111000 +
1#
#2280000
0#
#2300000
b111001 !
b111001 )
b111010 *
b111001 +
1#
#2320000
0#
#2340000
b111010 !
b111010 )
b111011 *
b111010 +
1#
#2360000
0#
#2380000
b111011 !
b111011 )
b111100 *
b111011 +
1#
#2400000
0#
#2420000
b111100 !
b111100 )
b111101 *
b111100 +
1#
#2440000
0#
#2460000
b111101 !
b111101 )
b111110 *
b111101 +
1#
#2480000
0#
#2500000
b111110 !
b111110 )
b111111 *
b111110 +
1#
#2520000
0#
#2540000
b111111 !
b111111 )
b1000000 *
b111111 +
1#
#2560000
0#
#2580000
b1000000 !
b1000000 )
b1000001 *
b1000000 +
1#
#2600000
0#
#2620000
b1000001 !
b1000001 )
b1000010 *
b1000001 +
1#
#2640000
0#
#2660000
b1000010 !
b1000010 )
b1000011 *
b1000010 +
1#
#2680000
0#
#2700000
b1000011 !
b1000011 )
b1000100 *
b1000011 +
1#
#2720000
0#
#2740000
b1000100 !
b1000100 )
b1000101 *
b1000100 +
1#
#2760000
0#
#2780000
b1000101 !
b1000101 )
b1000110 *
b1000101 +
1#
#2800000
0#
#2820000
b1000110 !
b1000110 )
b1000111 *
b1000110 +
1#
#2840000
0#
#2860000
b1000111 !
b1000111 )
b1001000 *
b1000111 +
1#
#2880000
0#
#2900000
b1001000 !
b1001000 )
b1001001 *
b1001000 +
1#
#2920000
0#
#2940000
b1001001 !
b1001001 )
b1001010 *
b1001001 +
1#
#2960000
0#
#2980000
b1001010 !
b1001010 )
b1001011 *
b1001010 +
1#
#3000000
0#
#3020000
b1001011 !
b1001011 )
b1001100 *
b1001011 +
1#
#3040000
0#
#3060000
b1001100 !
b1001100 )
b1001101 *
b1001100 +
1#
#3080000
0#
#3100000
b1001101 !
b1001101 )
b1001110 *
b1001101 +
1#
#3120000
0#
#3140000
b1001110 !
b1001110 )
b1001111 *
b1001110 +
1#
#3160000
0#
#3180000
b1001111 !
b1001111 )
b1010000 *
b1001111 +
1#
#3200000
0#
#3220000
b1010000 !
b1010000 )
b1010001 *
b1010000 +
1#
#3240000
0#
#3260000
b1010001 !
b1010001 )
b1010010 *
b1010001 +
1#
#3280000
0#
#3300000
b1010010 !
b1010010 )
b1010011 *
b1010010 +
1#
#3320000
0#
#3340000
b1010011 !
b1010011 )
b1010100 *
b1010011 +
1#
#3360000
0#
#3380000
b1010100 !
b1010100 )
b1010101 *
b1010100 +
1#
#3400000
0#
#3420000
b1010101 !
b1010101 )
b1010110 *
b1010101 +
1#
#3440000
0#
#3460000
b1010110 !
b1010110 )
b1010111 *
b1010110 +
1#
#3480000
0#
#3500000
b1010111 !
b1010111 )
b1011000 *
b1010111 +
1#
#3520000
0#
#3540000
b1011000 !
b1011000 )
b1011001 *
b1011000 +
1#
#3560000
0#
#3580000
b1011001 !
b1011001 )
b1011010 *
b1011001 +
1#
#3600000
0#
#3620000
b1011010 !
b1011010 )
b1011011 *
b1011010 +
1#
#3640000
0#
#3660000
b1011011 !
b1011011 )
b1011100 *
b1011011 +
1#
#3680000
0#
#3700000
b1011100 !
b1011100 )
b1011101 *
b1011100 +
1#
#3720000
0#
#3740000
b1011101 !
b1011101 )
b1011110 *
b1011101 +
1#
#3760000
0#
#3780000
b1011110 !
b1011110 )
b1011111 *
b1011110 +
1#
#3800000
0#
#3820000
b1011111 !
b1011111 )
b1100000 *
b1011111 +
1#
#3840000
0#
#3860000
b1100000 !
b1100000 )
b1100001 *
b1100000 +
1#
#3880000
0#
#3900000
b1100001 !
b1100001 )
b1100010 *
b1100001 +
1#
#3920000
0#
#3940000
b1100010 !
b1100010 )
b1100011 *
b1100010 +
1#
#3960000
0#
#3980000
b1100011 !
b1100011 )
b1100100 *
b1100011 +
1#
#4000000
0#
#4020000
b1100100 !
b1100100 )
b1100101 *
b1100100 +
1#
#4040000
0#
#4060000
b1100101 !
b1100101 )
b1100110 *
b1100101 +
1#
#4080000
0#
#4100000
b1100110 !
b1100110 )
b1100111 *
b1100110 +
1#
#4120000
0#
#4140000
b1100111 !
b1100111 )
b1101000 *
b1100111 +
1#
#4160000
0#
#4180000
b1101000 !
b1101000 )
b1101001 *
b1101000 +
1#
#4200000
0#
#4220000
b1101001 !
b1101001 )
b1101010 *
b1101001 +
1#
#4240000
0#
#4260000
b1101010 !
b1101010 )
b1101011 *
b1101010 +
1#
#4280000
0#
#4300000
b1101011 !
b1101011 )
b1101100 *
b1101011 +
1#
#4320000
0#
#4340000
b1101100 !
b1101100 )
b1101101 *
b1101100 +
1#
#4360000
0#
#4380000
b1101101 !
b1101101 )
b1101110 *
b1101101 +
1#
#4400000
0#
#4420000
b1101110 !
b1101110 )
b1101111 *
b1101110 +
1#
#4440000
0#
#4460000
b1101111 !
b1101111 )
b1110000 *
b1101111 +
1#
#4480000
0#
#4500000
b1110000 !
b1110000 )
b1110001 *
b1110000 +
1#
#4520000
0#
#4540000
b1110001 !
b1110001 )
b1110010 *
b1110001 +
1#
#4560000
0#
#4580000
b1110010 !
b1110010 )
b1110011 *
b1110010 +
1#
#4600000
0#
#4620000
b1110011 !
b1110011 )
b1110100 *
b1110011 +
1#
#4640000
0#
#4660000
b1110100 !
b1110100 )
b1110101 *
b1110100 +
1#
#4680000
0#
#4700000
b1110101 !
b1110101 )
b1110110 *
b1110101 +
1#
#4720000
0#
#4740000
b1110110 !
b1110110 )
b1110111 *
b1110110 +
1#
#4760000
0#
#4780000
b1110111 !
b1110111 )
b1111000 *
b1110111 +
1#
#4800000
0#
#4820000
b1111000 !
b1111000 )
b1111001 *
b1111000 +
1#
#4840000
0#
#4860000
b1111001 !
b1111001 )
b1111010 *
b1111001 +
1#
#4880000
0#
#4900000
b1111010 !
b1111010 )
b1111011 *
b1111010 +
1#
#4920000
0#
#4940000
b1111011 !
b1111011 )
b1111100 *
b1111011 +
1#
#4960000
0#
#4980000
b1111100 !
b1111100 )
b1111101 *
b1111100 +
1#
#5000000
0#
#5020000
b1111101 !
b1111101 )
b1111110 *
b1111101 +
1#
#5040000
0#
#5060000
b1111110 !
b1111110 )
b1111111 *
b1111110 +
1#
#5080000
0#
#5100000
b1111111 !
b1111111 )
b10000000 *
b1111111 +
1#
#5120000
0#
#5140000
b10000000 !
b10000000 )
b10000001 *
b10000000 +
1#
#5160000
0#
#5180000
b10000001 !
b10000001 )
b10000010 *
b10000001 +
1#
#5200000
0#
#5220000
b10000010 !
b10000010 )
b10000011 *
b10000010 +
1#
#5240000
0#
#5260000
b10000011 !
b10000011 )
b10000100 *
b10000011 +
1#
#5280000
0#
#5300000
b10000100 !
b10000100 )
b10000101 *
b10000100 +
1#
#5320000
0#
#5340000
b10000101 !
b10000101 )
b10000110 *
b10000101 +
1#
#5360000
0#
#5380000
b10000110 !
b10000110 )
b10000111 *
b10000110 +
1#
#5400000
0#
#5420000
b10000111 !
b10000111 )
b10001000 *
b10000111 +
1#
#5440000
0#
#5460000
b10001000 !
b10001000 )
b10001001 *
b10001000 +
1#
#5480000
0#
#5500000
b10001001 !
b10001001 )
b10001010 *
b10001001 +
1#
#5520000
0#
#5540000
b10001010 !
b10001010 )
b10001011 *
b10001010 +
1#
#5560000
0#
#5580000
b10001011 !
b10001011 )
b10001100 *
b10001011 +
1#
#5600000
0#
#5620000
b10001100 !
b10001100 )
b10001101 *
b10001100 +
1#
#5640000
0#
#5660000
b10001101 !
b10001101 )
b10001110 *
b10001101 +
1#
#5680000
0#
#5700000
b10001110 !
b10001110 )
b10001111 *
b10001110 +
1#
#5720000
0#
#5740000
b10001111 !
b10001111 )
b10010000 *
b10001111 +
1#
#5760000
0#
#5780000
b10010000 !
b10010000 )
b10010001 *
b10010000 +
1#
#5800000
0#
#5820000
b10010001 !
b10010001 )
b10010010 *
b10010001 +
1#
#5840000
0#
#5860000
b10010010 !
b10010010 )
b10010011 *
b10010010 +
1#
#5880000
0#
#5900000
b10010011 !
b10010011 )
b10010100 *
b10010011 +
1#
#5920000
0#
#5940000
b10010100 !
b10010100 )
b10010101 *
b10010100 +
1#
#5960000
0#
#5980000
b10010101 !
b10010101 )
b10010110 *
b10010101 +
1#
#6000000
0#
#6020000
b10010110 !
b10010110 )
b10010111 *
b10010110 +
1#
#6040000
0#
#6060000
b10010111 !
b10010111 )
b10011000 *
b10010111 +
1#
#6080000
0#
#6100000
b10011000 !
b10011000 )
b10011001 *
b10011000 +
1#
#6120000
0#
#6140000
b10011001 !
b10011001 )
b10011010 *
b10011001 +
1#
#6160000
0#
#6180000
b10011010 !
b10011010 )
b10011011 *
b10011010 +
1#
#6200000
0#
#6220000
b10011011 !
b10011011 )
b10011100 *
b10011011 +
1#
#6240000
0#
#6260000
b10011100 !
b10011100 )
b10011101 *
b10011100 +
1#
#6280000
0#
#6300000
b10011101 !
b10011101 )
b10011110 *
b10011101 +
1#
#6320000
0#
#6340000
b10011110 !
b10011110 )
b10011111 *
b10011110 +
1#
#6360000
0#
#6380000
b10011111 !
b10011111 )
b10100000 *
b10011111 +
1#
#6400000
0#
#6420000
b10100000 !
b10100000 )
b10100001 *
b10100000 +
1#
#6440000
0#
#6460000
b10100001 !
b10100001 )
b10100010 *
b10100001 +
1#
#6480000
0#
#6500000
b10100010 !
b10100010 )
b10100011 *
b10100010 +
1#
#6520000
0#
#6540000
b10100011 !
b10100011 )
b10100100 *
b10100011 +
1#
#6560000
0#
#6580000
b10100100 !
b10100100 )
b10100101 *
b10100100 +
1#
#6600000
0#
#6620000
b10100101 !
b10100101 )
b10100110 *
b10100101 +
1#
#6640000
0#
#6660000
b10100110 !
b10100110 )
b10100111 *
b10100110 +
1#
#6680000
0#
#6700000
b10100111 !
b10100111 )
b10101000 *
b10100111 +
1#
#6720000
0#
#6740000
b10101000 !
b10101000 )
b10101001 *
b10101000 +
1#
#6760000
0#
#6780000
b10101001 !
b10101001 )
b10101010 *
b10101001 +
1#
#6800000
0#
#6820000
b10101010 !
b10101010 )
b10101011 *
b10101010 +
1#
#6840000
0#
#6860000
b10101011 !
b10101011 )
b10101100 *
b10101011 +
1#
#6880000
0#
#6900000
b10101100 !
b10101100 )
b10101101 *
b10101100 +
1#
#6920000
0#
#6940000
b10101101 !
b10101101 )
b10101110 *
b10101101 +
1#
#6960000
0#
#6980000
b10101110 !
b10101110 )
b10101111 *
b10101110 +
1#
#7000000
0#
#7020000
b10101111 !
b10101111 )
b10110000 *
b10101111 +
1#
#7040000
0#
#7060000
b10110000 !
b10110000 )
b10110001 *
b10110000 +
1#
#7080000
0#
#7100000
b10110001 !
b10110001 )
b10110010 *
b10110001 +
1#
#7120000
0#
#7140000
b10110010 !
b10110010 )
b10110011 *
b10110010 +
1#
#7160000
0#
#7180000
b10110011 !
b10110011 )
b10110100 *
b10110011 +
1#
#7200000
0#
#7220000
b10110100 !
b10110100 )
b10110101 *
b10110100 +
1#
#7240000
0#
#7260000
b10110101 !
b10110101 )
b10110110 *
b10110101 +
1#
#7280000
0#
#7300000
b10110110 !
b10110110 )
b10110111 *
b10110110 +
1#
#7320000
0#
#7340000
b10110111 !
b10110111 )
b10111000 *
b10110111 +
1#
#7360000
0#
#7380000
b10111000 !
b10111000 )
b10111001 *
b10111000 +
1#
#7400000
0#
#7420000
b10111001 !
b10111001 )
b10111010 *
b10111001 +
1#
#7440000
0#
#7460000
b10111010 !
b10111010 )
b10111011 *
b10111010 +
1#
#7480000
0#
#7500000
b10111011 !
b10111011 )
b10111100 *
b10111011 +
1#
#7520000
0#
#7540000
b10111100 !
b10111100 )
b10111101 *
b10111100 +
1#
#7560000
0#
#7580000
b10111101 !
b10111101 )
b10111110 *
b10111101 +
1#
#7600000
0#
#7620000
b10111110 !
b10111110 )
b10111111 *
b10111110 +
1#
#7640000
0#
#7660000
b10111111 !
b10111111 )
b11000000 *
b10111111 +
1#
#7680000
0#
#7700000
b11000000 !
b11000000 )
b11000001 *
b11000000 +
1#
#7720000
0#
#7740000
b11000001 !
b11000001 )
b11000010 *
b11000001 +
1#
#7760000
0#
#7780000
b11000010 !
b11000010 )
b11000011 *
b11000010 +
1#
#7800000
0#
#7820000
b11000011 !
b11000011 )
b11000100 *
b11000011 +
1#
#7840000
0#
#7860000
b11000100 !
b11000100 )
b11000101 *
b11000100 +
1#
#7880000
0#
#7900000
b11000101 !
b11000101 )
b11000110 *
b11000101 +
1#
#7920000
0#
#7940000
b11000110 !
b11000110 )
b11000111 *
b11000110 +
1#
#7960000
0#
#7980000
b11000111 !
b11000111 )
b11001000 *
b11000111 +
1#
#8000000
0#
#8020000
b11001000 !
b11001000 )
b11001001 *
b11001000 +
1#
#8040000
0#
#8060000
b11001001 !
b11001001 )
b11001010 *
b11001001 +
1#
#8080000
0#
#8100000
b11001010 !
b11001010 )
b11001011 *
b11001010 +
1#
#8120000
0#
#8140000
b11001011 !
b11001011 )
b11001100 *
b11001011 +
1#
#8160000
0#
#8180000
b11001100 !
b11001100 )
b11001101 *
b11001100 +
1#
#8200000
0#
#8220000
b11001101 !
b11001101 )
b11001110 *
b11001101 +
1#
#8240000
0#
#8260000
b11001110 !
b11001110 )
b11001111 *
b11001110 +
1#
#8280000
0#
#8300000
b11001111 !
b11001111 )
b11010000 *
b11001111 +
1#
#8320000
0#
#8340000
b11010000 !
b11010000 )
b11010001 *
b11010000 +
1#
#8360000
0#
#8380000
b11010001 !
b11010001 )
b11010010 *
b11010001 +
1#
#8400000
0#
#8420000
b11010010 !
b11010010 )
b11010011 *
b11010010 +
1#
#8440000
0#
#8460000
b11010011 !
b11010011 )
b11010100 *
b11010011 +
1#
#8480000
0#
#8500000
b11010100 !
b11010100 )
b11010101 *
b11010100 +
1#
#8520000
0#
#8540000
b11010101 !
b11010101 )
b11010110 *
b11010101 +
1#
#8560000
0#
#8580000
b11010110 !
b11010110 )
b11010111 *
b11010110 +
1#
#8600000
0#
#8620000
b11010111 !
b11010111 )
b11011000 *
b11010111 +
1#
#8640000
0#
#8660000
b11011000 !
b11011000 )
b11011001 *
b11011000 +
1#
#8680000
0#
#8700000
b11011001 !
b11011001 )
b11011010 *
b11011001 +
1#
#8720000
0#
#8740000
b11011010 !
b11011010 )
b11011011 *
b11011010 +
1#
#8760000
0#
#8780000
b11011011 !
b11011011 )
b11011100 *
b11011011 +
1#
#8800000
0#
#8820000
b11011100 !
b11011100 )
b11011101 *
b11011100 +
1#
#8840000
0#
#8860000
b11011101 !
b11011101 )
b11011110 *
b11011101 +
1#
#8880000
0#
#8900000
b11011110 !
b11011110 )
b11011111 *
b11011110 +
1#
#8920000
0#
#8940000
b11011111 !
b11011111 )
b11100000 *
b11011111 +
1#
#8960000
0#
#8980000
b11100000 !
b11100000 )
b11100001 *
b11100000 +
1#
#9000000
0#
#9020000
b11100001 !
b11100001 )
b11100010 *
b11100001 +
1#
#9040000
0#
#9060000
b11100010 !
b11100010 )
b11100011 *
b11100010 +
1#
#9080000
0#
#9100000
b11100011 !
b11100011 )
b11100100 *
b11100011 +
1#
#9120000
0#
#9140000
b11100100 !
b11100100 )
b11100101 *
b11100100 +
1#
#9160000
0#
#9180000
b11100101 !
b11100101 )
b11100110 *
b11100101 +
1#
#9200000
0#
#9220000
b11100110 !
b11100110 )
b11100111 *
b11100110 +
1#
#9240000
0#
#9260000
b11100111 !
b11100111 )
b11101000 *
b11100111 +
1#
#9280000
0#
#9300000
b11101000 !
b11101000 )
b11101001 *
b11101000 +
1#
#9320000
0#
#9340000
b11101001 !
b11101001 )
b11101010 *
b11101001 +
1#
#9360000
0#
#9380000
b11101010 !
b11101010 )
b11101011 *
b11101010 +
1#
#9400000
0#
#9420000
b11101011 !
b11101011 )
b11101100 *
b11101011 +
1#
#9440000
0#
#9460000
b11101100 !
b11101100 )
b11101101 *
b11101100 +
1#
#9480000
0#
#9500000
b11101101 !
b11101101 )
b11101110 *
b11101101 +
1#
#9520000
0#
#9540000
b11101110 !
b11101110 )
b11101111 *
b11101110 +
1#
#9560000
0#
#9580000
b11101111 !
b11101111 )
b11110000 *
b11101111 +
1#
#9600000
0#
#9620000
b11110000 !
b11110000 )
b11110001 *
b11110000 +
1#
#9640000
0#
#9660000
b11110001 !
b11110001 )
b11110010 *
b11110001 +
1#
#9680000
0#
#9700000
b11110010 !
b11110010 )
b11110011 *
b11110010 +
1#
#9720000
0#
#9740000
b11110011 !
b11110011 )
b11110100 *
b11110011 +
1#
#9760000
0#
#9780000
b11110100 !
b11110100 )
b11110101 *
b11110100 +
1#
#9800000
0#
#9820000
b11110101 !
b11110101 )
b11110110 *
b11110101 +
1#
#9840000
0#
#9860000
b11110110 !
b11110110 )
b11110111 *
b11110110 +
1#
#9880000
0#
#9900000
b11110111 !
b11110111 )
b11111000 *
b11110111 +
1#
#9920000
0#
#9940000
b11111000 !
b11111000 )
b11111001 *
b11111000 +
1#
#9960000
0#
#9980000
b11111001 !
b11111001 )
b11111010 *
b11111001 +
1#
#10000000
0#
#10020000
b11111010 !
b11111010 )
b11111011 *
b11111010 +
1#
#10040000
0#
#10060000
b11111011 !
b11111011 )
b11111100 *
b11111011 +
1#
#10080000
0#
#10100000
b11111100 !
b11111100 )
b11111101 *
b11111100 +
1#
#10120000
0#
#10140000
b11111101 !
b11111101 )
b11111110 *
b11111101 +
1#
#10160000
0#
#10180000
b11111110 !
b11111110 )
b11111111 *
b11111110 +
1#
#10200000
0#
#10220000
b11111111 !
b11111111 )
b0 *
b11111111 +
1#
#10240000
0#
#10260000
b0 !
b0 )
b1 *
b0 +
1#
#10280000
0#
#10300000
b1 !
b1 )
b10 *
b1 +
1#
#10320000
0#
#10340000
b10 !
b10 )
b11 *
b10 +
1#
#10360000
0#
#10380000
b11 !
b11 )
b100 *
b11 +
1#
#10400000
0#
#10420000
b100 !
b100 )
b101 *
b100 +
1#
#10440000
0#
#10460000
b101 !
b101 )
b110 *
b101 +
1#
#10480000
0#
#10500000
b110 !
b110 )
b111 *
b110 +
1#
#10520000
0#
#10540000
b111 !
b111 )
b1000 *
b111 +
1#
#10560000
0#
#10580000
b1000 !
b1000 )
b1001 *
b1000 +
1#
#10600000
0#
#10620000
b1001 !
b1001 )
b1010 *
b1001 +
1#
#10640000
0#
#10660000
b1010 !
b1010 )
b1011 *
b1010 +
1#
#10680000
0#
#10700000
b1011 !
b1011 )
b1100 *
b1011 +
1#
#10720000
0#
#10740000
b1100 !
b1100 )
b1101 *
b1100 +
1#
#10760000
0#
#10780000
b1101 !
b1101 )
b1110 *
b1101 +
1#
#10800000
0#
#10820000
b1110 !
b1110 )
b1111 *
b1110 +
1#
#10840000
0#
#10860000
b1111 !
b1111 )
b10000 *
b1111 +
1#
#10880000
0#
#10900000
b10000 !
b10000 )
b10001 *
b10000 +
1#
#10920000
0#
#10940000
b10001 !
b10001 )
b10010 *
b10001 +
1#
#10960000
0#
#10980000
b10010 !
b10010 )
b10011 *
b10010 +
1#
#11000000
0#
#11020000
b10011 !
b10011 )
b10100 *
b10011 +
1#
#11040000
0#
#11060000
b10100 !
b10100 )
b10101 *
b10100 +
1#
#11080000
0#
#11100000
b10101 !
b10101 )
b10110 *
b10101 +
1#
#11120000
0#
#11140000
b10110 !
b10110 )
b10111 *
b10110 +
1#
#11160000
0#
#11180000
b10111 !
b10111 )
b11000 *
b10111 +
1#
#11200000
0#
#11220000
b11000 !
b11000 )
b11001 *
b11000 +
1#
#11240000
0#
#11260000
b11001 !
b11001 )
b11010 *
b11001 +
1#
#11280000
0#
#11300000
b11010 !
b11010 )
b11011 *
b11010 +
1#
#11320000
0#
#11340000
b11011 !
b11011 )
b11100 *
b11011 +
1#
#11360000
0#
#11380000
b11100 !
b11100 )
b11101 *
b11100 +
1#
#11400000
0#
#11420000
b11101 !
b11101 )
b11110 *
b11101 +
1#
#11440000
0#
#11460000
b11110 !
b11110 )
b11111 *
b11110 +
1#
#11480000
0#
#11500000
b11111 !
b11111 )
b100000 *
b11111 +
1#
#11520000
0#
#11540000
b100000 !
b100000 )
b100001 *
b100000 +
1#
#11560000
0#
#11580000
b100001 !
b100001 )
b100010 *
b100001 +
1#
#11600000
0#
#11620000
b100010 !
b100010 )
b100011 *
b100010 +
1#
#11640000
0#
#11660000
b100011 !
b100011 )
b100100 *
b100011 +
1#
#11680000
0#
#11700000
b100100 !
b100100 )
b100101 *
b100100 +
1#
#11720000
0#
#11740000
b100101 !
b100101 )
b100110 *
b100101 +
1#
#11760000
0#
#11780000
b100110 !
b100110 )
b100111 *
b100110 +
1#
#11800000
0#
#11820000
b100111 !
b100111 )
b101000 *
b100111 +
1#
#11840000
0#
#11860000
b101000 !
b101000 )
b101001 *
b101000 +
1#
#11880000
0#
#11900000
b101001 !
b101001 )
b101010 *
b101001 +
1#
#11920000
0#
#11940000
b101010 !
b101010 )
b101011 *
b101010 +
1#
#11960000
0#
#11980000
b101011 !
b101011 )
b101100 *
b101011 +
1#
#12000000
0#
#12020000
b101100 !
b101100 )
b101101 *
b101100 +
1#
#12040000
0#
#12060000
b101101 !
b101101 )
b101110 *
b101101 +
1#
#12080000
0#
#12100000
b101110 !
b101110 )
b101111 *
b101110 +
1#
#12120000
0#
#12140000
b101111 !
b101111 )
b110000 *
b101111 +
1#
#12160000
0#
#12180000
b110000 !
b110000 )
b110001 *
b110000 +
1#
#12200000
0#
#12220000
b110001 !
b110001 )
b110010 *
b110001 +
1#
#12240000
0#
#12260000
b110010 !
b110010 )
b110011 *
b110010 +
1#
#12280000
0#
#12300000
b110011 !
b110011 )
b110100 *
b110011 +
1#
#12320000
0#
#12340000
b110100 !
b110100 )
b110101 *
b110100 +
1#
#12360000
0#
#12380000
b110101 !
b110101 )
b110110 *
b110101 +
1#
#12400000
0#
#12420000
b110110 !
b110110 )
b110111 *
b110110 +
1#
#12440000
0#
#12460000
b110111 !
b110111 )
b111000 *
b110111 +
1#
#12480000
0#
#12500000
b111000 !
b111000 )
b111001 *
b111000 +
1#
#12520000
0#
#12540000
b111001 !
b111001 )
b111010 *
b111001 +
1#
#12560000
0#
#12580000
b111010 !
b111010 )
b111011 *
b111010 +
1#
#12600000
0#
#12620000
b111011 !
b111011 )
b111100 *
b111011 +
1#
#12640000
0#
#12660000
b111100 !
b111100 )
b111101 *
b111100 +
1#
#12680000
0#
#12700000
b111101 !
b111101 )
b111110 *
b111101 +
1#
#12720000
0#
#12740000
b111110 !
b111110 )
b111111 *
b111110 +
1#
#12760000
0#
#12780000
b111111 !
b111111 )
b1000000 *
b111111 +
1#
#12800000
0#
#12820000
b1000000 !
b1000000 )
b1000001 *
b1000000 +
1#
#12840000
0#
#12860000
b1000001 !
b1000001 )
b1000010 *
b1000001 +
1#
#12880000
0#
#12900000
b1000010 !
b1000010 )
b1000011 *
b1000010 +
1#
#12920000
0#
#12940000
b1000011 !
b1000011 )
b1000100 *
b1000011 +
1#
#12960000
0#
#12980000
b1000100 !
b1000100 )
b1000101 *
b1000100 +
1#
#13000000
0#
#13020000
b1000101 !
b1000101 )
b1000110 *
b1000101 +
1#
#13040000
0#
#13060000
b1000110 !
b1000110 )
b1000111 *
b1000110 +
1#
#13080000
0#
#13100000
b1000111 !
b1000111 )
b1001000 *
b1000111 +
1#
#13120000
0#
#13140000
b1001000 !
b1001000 )
b1001001 *
b1001000 +
1#
#13160000
0#
#13180000
b1001001 !
b1001001 )
b1001010 *
b1001001 +
1#
#13200000
0#
#13220000
b1001010 !
b1001010 )
b1001011 *
b1001010 +
1#
#13240000
0#
#13260000
b1001011 !
b1001011 )
b1001100 *
b1001011 +
1#
#13280000
0#
