Universal_mod_counter/counter.v
module counter
#(parameter N = 4,
 parameter M=10 )
(
    input wire clk,reset,up,en,
    input wire[N-1:0]start,
    output reg[N-1:0] out
);
reg[N-1:0]r_next,r_reg;
//memory segment 
always @(posedge clk,posedge reset) 
begin
if(reset==1'b0)
r_reg<=r_next;
else
r_reg<=0;    
end
//next state logic
always @* 
begin
if(en)//enabled
begin
if(up)//up
if(r_reg>=M)
r_next=0;
else
r_next=r_reg+1;
else//down
if(r_reg<=0)
r_next=start;
else
r_next=r_reg-1;    
end
else//not enabled
r_next=start;
end
//outlogic
always @* 
begin
out=r_reg;    
end    
endmodule

Universal_mod_counter/counter_tb.v
`timescale 1ns/1ps
module counter_tb();
localparam N = 8;
localparam M= 100;
reg clk,reset,up,en;
reg[N-1:0]start;
wire[N-1:0]out;
counter#(.N(N),.M(M)) circuit1
(
    .clk(clk),
    .reset(reset),
    .up(up),
    .en(en),
    .start(start),
    .out(out)
);
always
begin
    clk=~clk;
    #20;
end
initial begin
    $dumpfile("count.vcd");
    $dumpvars(0,counter_tb);
    clk=0;
    reset=1;
    en=0;
    up=0;
    start=8'b0000_0111;
    #40;
    reset=0;
    #40;
    en=1;
    #460;
    $finish;
end
initial begin
    $monitor("reset=%b, clk=%b, en=%b, up=%b, start=%b || out= %b",reset,clk,en,up,start,out);
end
endmodule

Universal_mod_counter/count.vcd
$date
	Thu Oct 27 19:31:21 2022
$end
$version
	Icarus Verilog
$end
$timescale
	1ps
$end
$scope module counter_tb $end
$var wire 8 ! out [7:0] $end
$var parameter 32 " M $end
$var parameter 32 # N $end
$var reg 1 $ clk $end
$var reg 1 % en $end
$var reg 1 & reset $end
$var reg 8 ' start [7:0] $end
$var reg 1 ( up $end
$scope module circuit1 $end
$var wire 1 $ clk $end
$var wire 1 % en $end
$var wire 1 & reset $end
$var wire 8 ) start [7:0] $end
$var wire 1 ( up $end
$var parameter 32 * M $end
$var parameter 32 + N $end
$var reg 8 , out [7:0] $end
$var reg 8 - r_next [7:0] $end
$var reg 8 . r_reg [7:0] $end
$upscope $end
$upscope $end
$enddefinitions $end
$comment Show the parameter values. $end
$dumpall
b1000 +
b1100100 *
b1000 #
b1100100 "
$end
#0
$dumpvars
b0 .
b111 -
b0 ,
b111 )
0(
b111 '
1&
0%
0$
b0 !
$end
#20000
1$
#40000
0$
0&
#60000
b111 !
b111 ,
b111 .
1$
#80000
b110 -
0$
1%
#100000
b110 !
b110 ,
b101 -
b110 .
1$
#120000
0$
#140000
b101 !
b101 ,
b100 -
b101 .
1$
#160000
0$
#180000
b100 !
b100 ,
b11 -
b100 .
1$
#200000
0$
#220000
b11 !
b11 ,
b10 -
b11 .
1$
#240000
0$
#260000
b10 !
b10 ,
b1 -
b10 .
1$
#280000
0$
#300000
b1 !
b1 ,
b0 -
b1 .
1$
#320000
0$
#340000
b0 !
b0 ,
b111 -
b0 .
1$
#360000
0$
#380000
b111 !
b111 ,
b110 -
b111 .
1$
#400000
0$
#420000
b110 !
b110 ,
b101 -
b110 .
1$
#440000
0$
#460000
b101 !
b101 ,
b100 -
b101 .
1$
#480000
0$
#500000
b100 !
b100 ,
b11 -
b100 .
1$
#520000
0$
#540000
b11 !
b11 ,
b10 -
b11 .
1$
